bakalariapi/__init__.py
bakalariapi/bakalari.py
bakalariapi/exceptions.py
bakalariapi/looting.py
bakalariapi/objects.py
bakalariapi/seleniumhandler.py
bakalariapi/serialization.py
bakalariapi/sessions.py
bakalariapi/utils.py
bakalariapi/modules/__init__.py
bakalariapi/modules/documents.py
bakalariapi/modules/grades.py
bakalariapi/modules/homeworks.py
bakalariapi/modules/komens.py
bakalariapi/modules/meetings.py
bakalariapi/modules/timetable.py
bakalarishell/__init__.py
bakalarishell/__main__.py
bakalarishell/main.py
bakalarishell/shell.py
BakalariAPI-4.0.0.dist-info/METADATA
BakalariAPI-4.0.0.dist-info/WHEEL
BakalariAPI-4.0.0.dist-info/entry_points.txt
BakalariAPI-4.0.0.dist-info/top_level.txt
BakalariAPI-4.0.0.dist-info/RECORD
