Metadata-Version: 2.1
Name: BakalariAPI
Version: 4.0.0
Summary: Rádoby API pro Bakaláře
Home-page: https://github.com/Hackrrr/BakalariAPI/
Author: Hackrrr
License: MIT
Platform: UNKNOWN
Requires-Python: >=3.9
Requires-Dist: bs4
Requires-Dist: platformdirs
Requires-Dist: prompt-toolkit (>=3.0.9)
Requires-Dist: requests
Requires-Dist: rich
Requires-Dist: selenium
Requires-Dist: typing-extensions (>=3.10)
